mangoui/__init__.py
mangoui/widget_tool.py
mangoui/components/__init__.py
mangoui/components/diglog_widget.py
mangoui/components/message.py
mangoui/components/notification.py
mangoui/components/right_button.py
mangoui/components/search_widget.py
mangoui/components/table_list.py
mangoui/components/title_info.py
mangoui/enums/__init__.py
mangoui/enums/enums.py
mangoui/exceptins/__init__.py
mangoui/models/__init__.py
mangoui/models/models.py
mangoui/resources/__init__.py
mangoui/resources/app_rc.py
mangoui/settings/__init__.py
mangoui/settings/settings.py
mangoui/styles/__init__.py
mangoui/styles/generate_qss.py
mangoui/styles/qss.py
mangoui/widgets/__init__.py
mangoui/widgets/charts/__init__.py
mangoui/widgets/charts/line.py
mangoui/widgets/charts/pie.py
mangoui/widgets/container/__init__.py
mangoui/widgets/container/mango_card.py
mangoui/widgets/container/mango_group_box.py
mangoui/widgets/container/mango_stacked_widget.py
mangoui/widgets/container/mango_tool_box.py
mangoui/widgets/display/__init__.py
mangoui/widgets/display/mango_calendar_widget.py
mangoui/widgets/display/mango_circular_progress.py
mangoui/widgets/display/mango_label.py
mangoui/widgets/display/mango_lcd_number.py
mangoui/widgets/display/mango_line.py
mangoui/widgets/display/mango_list_view.py
mangoui/widgets/display/mango_list_widget.py
mangoui/widgets/display/mango_message.py
mangoui/widgets/display/mango_notification.py
mangoui/widgets/display/mango_pagination.py
mangoui/widgets/display/mango_progress_bar.py
mangoui/widgets/display/mango_status_bar.py
mangoui/widgets/display/mango_table.py
mangoui/widgets/display/mango_table_view.py
mangoui/widgets/display/mango_table_widget.py
mangoui/widgets/display/mango_tree_view.py
mangoui/widgets/display/mango_tree_widget.py
mangoui/widgets/input/__init__.py
mangoui/widgets/input/mang_time_edit.py
mangoui/widgets/input/mango_cascader.py
mangoui/widgets/input/mango_checkbox.py
mangoui/widgets/input/mango_combo_box.py
mangoui/widgets/input/mango_date_edit.py
mangoui-4.0.3.dist-info/licenses/LICENSE
mangoui-4.0.3.dist-info/METADATA
mangoui-4.0.3.dist-info/WHEEL
mangoui-4.0.3.dist-info/top_level.txt
mangoui-4.0.3.dist-info/RECORD
