Metadata-Version: 2.4
Name: mangoui
Version: 4.0.3
Summary: UI组件库
Home-page: https://gitee.com/mao-peng/MangoUi
Author: 毛鹏
Author-email: 729164035@qq.com
License-Expression: MIT
Classifier: Programming Language :: Python :: 3.10
Classifier: Programming Language :: Python :: 3.11
Classifier: Programming Language :: Python :: 3.12
Classifier: Programming Language :: Python :: 3.13
Classifier: Operating System :: OS Independent
Requires-Python: >=3.10
License-File: LICENSE
Requires-Dist: pydantic>=2.9.2
Requires-Dist: pyside6>=6.8.1
Requires-Dist: matplotlib>=3.9.2
Requires-Dist: numpy>=2.2.0
Requires-Dist: pyqtgraph>=0.13.7
Dynamic: author
Dynamic: author-email
Dynamic: classifier
Dynamic: description
Dynamic: description-content-type
Dynamic: home-page
Dynamic: license-file
Dynamic: license-expression
Dynamic: requires-dist
Dynamic: requires-python
Dynamic: summary
